cmd/__init__.py
cmd/gitlab_cmds/cli.py
cmd/gitlab_cmds/conf.py
cmd/gitlab_cmds/group.py
cmd/gitlab_cmds/info.py
cmd/gitlab_cmds/main.py
cmd/gitlab_cmds/project.py
cmd/gitlab_cmds/__init__.py
gitlab/helper.py
gitlab/__init__.py
scm_git-1.2.4.dist-info/DESCRIPTION.rst
scm_git-1.2.4.dist-info/entry_points.txt
scm_git-1.2.4.dist-info/METADATA
scm_git-1.2.4.dist-info/metadata.json
scm_git-1.2.4.dist-info/RECORD
scm_git-1.2.4.dist-info/top_level.txt
scm_git-1.2.4.dist-info/WHEEL
utils/utils.py
utils/__init__.py
