Metadata-Version: 2.0
Name: scm-git
Version: 1.2.4
Summary: A tool that operate GitLab remotely
Home-page: https://github.com/pypa/sampleproject
Author: Nokia 3GC OSP CI Team
Author-email: kevin.j.wang@nokia-sbell.com
License: MIT
Keywords: SCM GitLab setuptools development
Platform: UNKNOWN
Classifier: Development Status :: 4 - Beta
Classifier: Intended Audience :: Developers
Classifier: Topic :: System :: Shells
Classifier: License :: OSI Approved :: MIT License
Classifier: Programming Language :: Python :: 2.7
Classifier: Programming Language :: Python :: 3
Classifier: Programming Language :: Python :: 3.3
Classifier: Programming Language :: Python :: 3.4
Classifier: Programming Language :: Python :: 3.5
Requires-Dist: request
Requires-Dist: urllib3[secure]
Requires-Dist: click
